<?xml version = '1.0' encoding = 'UTF-8'?>
<TableProxyOraclev12c class="oracle.dbtools.crest.model.design.storage.oracle.v12c.TableProxyOraclev12c" name="ONT_PROD_COLOR" directorySegmentName="seg_0" id="3EBD86C2-3B00-370A-C215-3371A4706FC8">
<createdBy>saifur</createdBy>
<createdTime>2017-07-25 19:52:25 UTC</createdTime>
<ownerDesignName>HSM_dm_design</ownerDesignName>
<schemaObject>57E87950-27FA-50DF-9F1D-54C619FF620D</schemaObject>
<logging>YES</logging>
<partitionedRowMovement>DISABLE</partitionedRowMovement>
<segment>24B0D98C-B9C1-E5BD-CE83-5E110181BA06</segment>
<tableSpace>694DAC9F-DB98-14CC-E543-33A6AB57EA89</tableSpace>
<temporaryChanged>false</temporaryChanged>
<accessDriverType>oracle_loader</accessDriverType>
<rejectLimit></rejectLimit>
<inMemory>NO</inMemory>
<columnProxies itemClass="oracle.dbtools.crest.model.design.storage.oracle.v12c.ColumnProxyOraclev12c">
<ColumnProxy name="OPC_COLOR_ID" id="1D6122F7-B19D-7FFE-0473-86B03386FC4C">
<createdBy>saifur</createdBy>
<createdTime>2017-07-25 19:52:25 UTC</createdTime>
<ownerDesignName>HSM_dm_design</ownerDesignName>
</ColumnProxy>
<ColumnProxy name="OPC_PROD_ID" id="BF01BCD6-D4A9-3FC2-AB45-7D86706351DC">
<createdBy>saifur</createdBy>
<createdTime>2017-07-25 19:52:25 UTC</createdTime>
<ownerDesignName>HSM_dm_design</ownerDesignName>
</ColumnProxy>
</columnProxies>
</TableProxyOraclev12c>